eng.py
eng_tools_by_josh-0.1.dist-info/licenses/LICENSE
eng_tools_by_josh-0.1.dist-info/METADATA
eng_tools_by_josh-0.1.dist-info/WHEEL
eng_tools_by_josh-0.1.dist-info/top_level.txt
eng_tools_by_josh-0.1.dist-info/RECORD
