Metadata-Version: 2.4
Name: eng-tools-by-josh
Version: 0.1
Summary: A simple module for STEM!
Author: Joshua
License: MIT
License-File: LICENSE
Dynamic: author
Dynamic: description
Dynamic: description-content-type
Dynamic: license
Dynamic: license-file
Dynamic: summary
